cube_http/__init__.py
cube_http/clients.py
cube_http/exc/__init__.py
cube_http/exc/v1/__init__.py
cube_http/exc/v1/_base.py
cube_http/exc/v1/load.py
cube_http/exc/v1/meta.py
cube_http/exc/v1/sql.py
cube_http/py.typed
cube_http/routes/__init__.py
cube_http/routes/_base.py
cube_http/routes/v1/__init__.py
cube_http/routes/v1/load.py
cube_http/routes/v1/meta.py
cube_http/routes/v1/sql.py
cube_http/types/_base.py
cube_http/types/v1/__init__.py
cube_http/types/v1/load_request.py
cube_http/types/v1/load_response.py
cube_http/types/v1/meta_request.py
cube_http/types/v1/meta_response.py
cube_http/types/v1/operators.py
cube_http/types/v1/sql_request.py
cube_http/types/v1/sql_response.py
cube_http/types/v1/time_granularities.py
cube_http_client-0.6.1.dist-info/METADATA
cube_http_client-0.6.1.dist-info/WHEEL
cube_http_client-0.6.1.dist-info/entry_points.txt
cube_http_client-0.6.1.dist-info/licenses/LICENSE
cube_http_client-0.6.1.dist-info/RECORD
