Metadata-Version: 2.1
Name: cube-http-client
Version: 0.6.1
Summary: Pythonic HTTP client for Cube.js REST API (sync + async)
Keywords: cube.js,cube js,cube.dev,cube
Author-Email: Michael Harris <mharris@definite.app>
License: MIT
Project-URL: homepage, https://github.com/mharrisb1/cube-http-client
Project-URL: repository, https://github.com/mharrisb1/cube-http-client
Project-URL: documentation, https://github.com/mharrisb1/cube-http-client
Requires-Python: <4.0,>=3.10
Requires-Dist: httpx>=0.27
Requires-Dist: pydantic<3,>=2
